smiles_featurizers/__init__.py
smiles_featurizers/bart_featurizer.py
smiles_featurizers/base_featurizer.py
smiles_featurizers/bert_featurizer.py
smiles_featurizers/sentence_transformers_featurizer.py
smiles_featurizers/simcse_featurizer.py
smiles_featurizers-1.0.8.dist-info/LICENSE
smiles_featurizers-1.0.8.dist-info/METADATA
smiles_featurizers-1.0.8.dist-info/WHEEL
smiles_featurizers-1.0.8.dist-info/top_level.txt
smiles_featurizers-1.0.8.dist-info/RECORD
