Metadata-Version: 2.1
Name: smiles-featurizers
Version: 1.0.8
Summary: A python library for extracting molecular SMILES embeddings from language models pre-trained with various objectives and/or architectures.
Home-page: https://github.com/MoleculeTransformers/smiles-featurizers
Author: Shahrukh Khan
Author-email: sk28671@gmail.com
Classifier: Intended Audience :: Developers
Classifier: Programming Language :: Python
Classifier: Programming Language :: Python :: 3.8
Classifier: License :: OSI Approved :: MIT License
Classifier: Operating System :: OS Independent
Requires-Python: >=3.8
License-File: LICENSE
Requires-Dist: torch (==1.8.1)
Requires-Dist: torchvision (==0.9.1)
Requires-Dist: torchaudio (==0.8.1)
Requires-Dist: transformers (==4.6.1)
Requires-Dist: farm (==0.8.0)
Requires-Dist: simcse (==0.4)
Requires-Dist: apex (==0.9.10.dev0)
Requires-Dist: sentence-transformers
